launch/README.md
launch/__init__.py
launch/cli/__init__.py
launch/cli/bin.py
launch/cli/bundles.py
launch/cli/client.py
launch/cli/endpoints.py
launch/client.py
launch/clientlib/README.md
launch/clientlib/__init__.py
launch/clientlib/batching/__init__.py
launch/clientlib/batching/implementation.py
launch/clientlib/batching/named_arrays.py
launch/clientlib/batching/single_array.py
launch/clientlib/batching/types.py
launch/clientlib/core.py
launch/clientlib/demonstration.py
launch/clientlib/deployment.py
launch/clientlib/exe/__init__.py
launch/clientlib/exe/run_service.py
launch/clientlib/full_service.py
launch/clientlib/http.py
launch/clientlib/loader.py
launch/clientlib/model.py
launch/clientlib/model_service/__init__.py
launch/clientlib/model_service/implementation.py
launch/clientlib/model_service/named_arrays.py
launch/clientlib/model_service/single_array.py
launch/clientlib/model_service/types.py
launch/clientlib/object_conf_from_std_ml_serve.py
launch/clientlib/pipeline.py
launch/clientlib/service.py
launch/clientlib/triton.py
launch/clientlib/types.py
launch/clientlib/utils.py
launch/connection.py
launch/constants.py
launch/errors.py
launch/find_packages.py
launch/hooks.py
launch/logger.py
launch/make_batch_file.py
launch/model_bundle.py
launch/model_endpoint.py
launch/pipeline/__init__.py
launch/pipeline/deployment.py
launch/pipeline/runtime.py
launch/pipeline/service.py
launch/pipeline/utils.py
launch/request_validation.py
launch/retry_strategy.py
launch/utils.py
scale_launch-0.3.3.dist-info/entry_points.txt
scale_launch-0.3.3.dist-info/WHEEL
scale_launch-0.3.3.dist-info/METADATA
scale_launch-0.3.3.dist-info/RECORD
