Metadata-Version: 2.1
Name: scale-launch
Version: 0.3.3
Summary: The official Python client library for Launch, the Data Platform for AI
Home-page: https://scale.com/
Author: Your Name
Author-email: you@example.com
Requires-Python: >=3.7,<4.0
Classifier: Programming Language :: Python :: 3
Classifier: Programming Language :: Python :: 3.7
Classifier: Programming Language :: Python :: 3.8
Classifier: Programming Language :: Python :: 3.9
Requires-Dist: cloudpickle (>=2.0.0,<3.0.0)
Requires-Dist: dataclasses-json (>=0.5.7,<0.6.0)
Requires-Dist: deprecation (>=2.1.0,<3.0.0)
Requires-Dist: pyyaml (>=5.3.1,<7.0.0)
Requires-Dist: requests (>=2.25.1,<3.0.0)
Requires-Dist: rich (>=12.0.0,<13.0.0)
Requires-Dist: typing-extensions (>=4.1.1,<5.0.0)
Project-URL: Repository, https://github.com/scaleapi/launch-python-client
